machinerry.py
machinerry-0.2.6.dist-info/LICENSE.txt
machinerry-0.2.6.dist-info/METADATA
machinerry-0.2.6.dist-info/WHEEL
machinerry-0.2.6.dist-info/namespace_packages.txt
machinerry-0.2.6.dist-info/top_level.txt
machinerry-0.2.6.dist-info/RECORD
