Metadata-Version: 2.1
Name: machinerry
Version: 0.2.6
Summary: CherryPy-based framework for running tasks repeatedly.
Home-page: https://github.com/the-allanc/machinerry/
Author: Allan Crooks
Author-email: allan@increment.one
License: MIT
Classifier: Development Status :: 4 - Beta
Classifier: Environment :: Web Environment
Classifier: Framework :: CherryPy
Classifier: Intended Audience :: Developers
Classifier: License :: OSI Approved :: MIT License
Classifier: Operating System :: OS Independent
Classifier: Programming Language :: Python :: 2.7
Classifier: Programming Language :: Python :: 3
Classifier: Topic :: Software Development :: Libraries
Classifier: Topic :: Software Development :: Libraries :: Python Modules
Classifier: Topic :: Internet :: WWW/HTTP
Classifier: Topic :: Internet :: WWW/HTTP :: Dynamic Content
Classifier: Topic :: Internet :: WWW/HTTP :: HTTP Servers
Classifier: Topic :: Internet :: WWW/HTTP :: WSGI
Classifier: Topic :: Internet :: WWW/HTTP :: WSGI :: Application
Classifier: Topic :: Internet :: WWW/HTTP :: WSGI :: Server
Requires-Python: >=2.7
License-File: LICENSE.txt
Requires-Dist: CherryPy
Requires-Dist: requests
Requires-Dist: six
Provides-Extra: docs
Requires-Dist: sphinx; extra == "docs"
Requires-Dist: jaraco.packaging>=3.2; extra == "docs"
Requires-Dist: rst.linker>=1.9; extra == "docs"
Requires-Dist: allanc-sphinx[yeen]>=0.2; extra == "docs"
Provides-Extra: lint
Requires-Dist: flake8; extra == "lint"
Requires-Dist: radon; extra == "lint"
Requires-Dist: pylint; extra == "lint"
Provides-Extra: testing
Requires-Dist: pytest>=3.5; extra == "testing"
Requires-Dist: pytest-sugar>=0.9.1; extra == "testing"
Requires-Dist: collective.checkdocs; extra == "testing"
Requires-Dist: pytest-cov; extra == "testing"
Requires-Dist: pylint; extra == "testing"
